README
setup.py
pyrcws/__init__.py
pyrcws/main.py
pyrcws/util.py
pyrcws.egg-info/PKG-INFO
pyrcws.egg-info/SOURCES.txt
pyrcws.egg-info/dependency_links.txt
pyrcws.egg-info/not-zip-safe
pyrcws.egg-info/requires.txt
pyrcws.egg-info/top_level.txt