Metadata-Version: 1.1
Name: pyrcws
Version: 0.2.5
Summary: pyrcws
Home-page: http://github.com/rpedigoni/pyrcws
Author: Renato Pedigoni
Author-email: renatopedigoni@gmail.com
License: BSD
Keywords: redecard
Platform: UNKNOWN
Classifier: Programming Language :: Python
Classifier: Topic :: Software Development :: Libraries :: Python Modules
